mcp_weather_server/__init__.py
mcp_weather_server/__main__.py
mcp_weather_server/server-see.py
mcp_weather_server/server.py
mcp_weather_server/utils.py
mseep_mcp_weather_server-0.2.3.dist-info/licenses/LICENSE
mseep_mcp_weather_server-0.2.3.dist-info/METADATA
mseep_mcp_weather_server-0.2.3.dist-info/WHEEL
mseep_mcp_weather_server-0.2.3.dist-info/entry_points.txt
mseep_mcp_weather_server-0.2.3.dist-info/top_level.txt
mseep_mcp_weather_server-0.2.3.dist-info/RECORD
