Metadata-Version: 2.4
Name: mseep-mcp_weather_server
Version: 0.2.3
Summary: An MCP server for weather information
Author-email: mseep <support@skydeck.ai>
Project-URL: Source, https://github.com/isdaniel/mcp_weather_server
Requires-Python: >=3.13
License-File: LICENSE
Requires-Dist: mcp>=1.0.0
Requires-Dist: argparse>=1.4.0
Requires-Dist: httpx>=0.28.1
Requires-Dist: mcp[cli]>=1.2.1
Requires-Dist: python-dotenv>=1.0.1
Requires-Dist: python-dateutil>=2.8.2
Dynamic: license-file
